matchingsplit/__init__.py
matchingsplit-0.1.2.dist-info/METADATA
matchingsplit-0.1.2.dist-info/WHEEL
matchingsplit-0.1.2.dist-info/licenses/LICENSE
matchingsplit-0.1.2.dist-info/RECORD
