Metadata-Version: 2.1
Name: matchingsplit
Version: 0.1.2
Summary: Split a string or group a collection of words into a list by matching another list of similar words, to create accurate subtitles from the actual script and inaccurate (generated) subtitles.
Project-URL: Homepage, https://github.com/sayanarijit/matchingsplit
Author-email: Arijit Basu <sayanarijit@gmail.com>
Maintainer-email: Arijit Basu <sayanarijit@gmail.com>
License: MIT License
License-File: LICENSE
Keywords: fixer,fuzzy,splitter,subtitles,words
Classifier: Development Status :: 3 - Alpha
Classifier: Intended Audience :: Developers
Classifier: License :: OSI Approved :: MIT License
Classifier: Programming Language :: Python :: 3
Classifier: Programming Language :: Python :: 3.10
Classifier: Programming Language :: Python :: 3.11
Classifier: Topic :: Text Processing
Requires-Python: >=3.10
Requires-Dist: thefuzz>=0.20
Provides-Extra: test
Requires-Dist: pytest; extra == 'test'
Requires-Dist: pytest-cov; extra == 'test'
